<annotation>
    <folder>img_dir</folder>
    <filename>000737.jpg</filename>
    <path>L:\项目\目标检测\streamlit-img-label-main\img_dir\000737.jpg</path>
    <source>
        <database>Unknown</database>
    </source>
    <size>
        <width>425</width>
        <height>319</height>
        <depth>3</depth>
    </size>
    <segmented>0</segmented>
    <object>
        <name>安全帽</name>
        <pose>Unspecified</pose>
        <truncated>0</truncated>
        <difficult>0</difficult>
        <bndbox>
            <xmin>40</xmin>
            <ymin>56</ymin>
            <xmax>104</xmax>
            <ymax>104</ymax>
        </bndbox>
    </object>    <object>
        <name>安全帽</name>
        <pose>Unspecified</pose>
        <truncated>0</truncated>
        <difficult>0</difficult>
        <bndbox>
            <xmin>241</xmin>
            <ymin>74</ymin>
            <xmax>305</xmax>
            <ymax>119</ymax>
        </bndbox>
    </object>
</annotation>
